[
  {
    "title" : "Gilang",
    "src" : "https://encrypted-tbn0.gstatic.com/images?q=tbn:ANd9GcRjdM9y-IbD5Jw-q0p7DDxrCF6THf2F3ycTcq9PkzuRo_49nFFrPDPJl-E7&s=100",
    "desc" : "yy",
    "created" : "2025/5/21",
    "uploader" : "Gilang"
  }
  {
    "title" : "Gilang",
    "src" : "https://encrypted-tbn0.gstatic.com/images?q=tbn:ANd9GcRZqBRbiXs8SMGNsd91yaHB0Vz2hy7T6lTduoRmzRZ1p5NyL6TtTCLDaAVq&s=10",
    "desc" : "yy",
    "created" : "2025/5/21",
    "uploader" : "Gilang"
  }
  {
    "title" : "Gilang",
    "src" : "https://encrypted-tbn0.gstatic.com/images?q=tbn:ANd9GcRFaDuuZx4ISWE1MYrx2Gvm2WRdBokMbhR06sV5EdGpoQHfnqlC-3Nmkv3E&s=10",
    "desc" : "yy",
    "created" : "2025/5/21",
    "uploader" : "Gilang"
  }
  {
    "title" : "Gilang",
    "src" : "https://i.imgur.com/tmqqQYK.jpeg",
    "desc" : "yy",
    "created" : "2025/5/21",
    "uploader" : "Gilang"
  }
  {
    "title" : "Gilang",
    "src" : "https://encrypted-tbn0.gstatic.com/images?q=tbn:ANd9GcQsWopXADFgalXCxGnUjxKbBIa9wQyMI4HDYAaPyPjZlDhAFj6S4PQQ0LM&s=10",
    "desc" : "yy",
    "created" : "2025/5/21",
    "uploader" : "Gilang"
  },
  {
    "title" : "Gilang",
    "src" : "https://encrypted-tbn0.gstatic.com/images?q=tbn:ANd9GcRiqYHSR-WoEeHVIBdaFtXKzwGl8F8kUe8gsMmxoLwXEX2McKma1PePneo&s=10",
    "desc" : "yy",
    "created" : "2025/5/21",
    "uploader" : "Gilang"
  },
]
